LICENSE
MANIFEST.in
README.md
setup.cfg
setup.py
zephserver/__init__.py
zephserver/main.py
zephserver/settings.py
zephserver.egg-info/PKG-INFO
zephserver.egg-info/SOURCES.txt
zephserver.egg-info/dependency_links.txt
zephserver.egg-info/entry_points.txt
zephserver.egg-info/not-zip-safe
zephserver.egg-info/requires.txt
zephserver.egg-info/top_level.txt
zephserver/admin/__init__.py
zephserver/admin/command.py
zephserver/infra/__init__.py
zephserver/infra/bootstrap.py
zephserver/infra/cluster_adapter.py
zephserver/infra/external_control.py
zephserver/infra/service_manager.py
zephserver/service/__init__.py
zephserver/service/clientsocket_service.py
zephserver/service/db_service.py
zephserver/service/django_session_service.py
zephserver/service/roomhandler_service.py
zephserver/service/routeur_service.py
zephserver/service/service_interface.py
zephserver/task/__init__.py
zephserver/task/task_abstract.py
zephserver/task/task_interface.py
zephserver/task/task_ping.py
zephserver/test/__init__.py
zephserver/test/setup_tests.py
zephserver/test/test_cluster_controller.py
zephserver/test/test_service_manager.py
zephserver/test/utils/__init__.py
zephserver/test/utils/dummy_service.py
zephserver/utils/__init__.py
zephserver/utils/decorator/__init__.py
zephserver/utils/decorator/accessdecorator.py
zephserver/utils/decorator/sessiondecorator.py
zephserver/utils/roomhandler/__init__.py
zephserver/utils/roomhandler/roomhandler.py