Metadata-Version: 1.1
Name: zephserver
Version: 0.1.27
Summary: Python service manager that can be used as a websocket server
Home-page: https://github.com/CDSP/zephserver
Author: CDSP
Author-email: zephserver-scpolst@sciencespo.fr
License: UNKNOWN
Keywords: websocket,zeph,server,zephserver
Platform: UNKNOWN
Classifier: Operating System :: POSIX
Classifier: Development Status :: 2 - Pre-Alpha
Classifier: License :: OSI Approved :: GNU General Public License v3 (GPLv3)
Classifier: Programming Language :: Python :: 2.7
